pacalc/__init__.py
pacalc/pacalc.py
pa_calc-0.1.0.dist-info/LICENSE.md
pa_calc-0.1.0.dist-info/METADATA
pa_calc-0.1.0.dist-info/WHEEL
pa_calc-0.1.0.dist-info/top_level.txt
pa_calc-0.1.0.dist-info/RECORD
