Metadata-Version: 2.1
Name: pa-calc
Version: 0.1.0
Summary: Demo library
Home-page: https://pa_calc.readthedocs.io/
Author: Javier Jofre
Author-email: javier.jofre@polymtl.ca
License: GPLv3
Platform: UNKNOWN
Classifier: Intended Audience :: Developers
Classifier: License :: OSI Approved :: GNU Affero General Public License v3
Classifier: Programming Language :: Python
Classifier: Programming Language :: Python :: 3
Classifier: Programming Language :: Python :: 3.6
Classifier: Programming Language :: Python :: 3.7
Classifier: Programming Language :: Python :: 3.8
Classifier: Programming Language :: Python :: 3.9
Classifier: Operating System :: OS Independent
Requires-Dist: numpy
Requires-Dist: itertools
